ftable/__init__.py
ftable/test.py
ftable/csum_test/test.py
ftable-0.1.3.dist-info/METADATA
ftable-0.1.3.dist-info/WHEEL
ftable-0.1.3.dist-info/top_level.txt
ftable-0.1.3.dist-info/RECORD
